{
  "format_version": "1.8.0",
  "animations": {
    "animation.obelisk_sentinel.idle": {
      "loop": true,
      "animation_length": 2.0,
      "bones": {
        "core": {
          "position": {
            "0.0": [
              0,
              0,
              0
            ],
            "1.0": [
              0,
              0.35,
              0
            ],
            "2.0": [
              0,
              0,
              0
            ]
          },
          "rotation": {
            "0.0": [
              0,
              0,
              0
            ],
            "2.0": [
              0,
              8,
              0
            ]
          }
        },
        "shard1": {
          "rotation": {
            "0.0": [
              0,
              0,
              0
            ],
            "2.0": [
              0,
              360,
              0
            ]
          }
        },
        "shard2": {
          "rotation": {
            "0.0": [
              0,
              90,
              0
            ],
            "2.0": [
              0,
              450,
              0
            ]
          }
        },
        "shard3": {
          "rotation": {
            "0.0": [
              0,
              180,
              0
            ],
            "2.0": [
              0,
              540,
              0
            ]
          }
        },
        "shard4": {
          "rotation": {
            "0.0": [
              0,
              270,
              0
            ],
            "2.0": [
              0,
              630,
              0
            ]
          }
        }
      }
    },
    "animation.obelisk_sentinel.walk": {
      "loop": true,
      "animation_length": 1.2,
      "bones": {
        "core": {
          "position": {
            "0.0": [
              0,
              0,
              0
            ],
            "1.0": [
              0,
              0.35,
              0
            ],
            "2.0": [
              0,
              0,
              0
            ]
          },
          "rotation": {
            "0.0": [
              0,
              0,
              0
            ],
            "2.0": [
              0,
              8,
              0
            ]
          }
        },
        "shard1": {
          "rotation": {
            "0.0": [
              0,
              0,
              0
            ],
            "2.0": [
              0,
              360,
              0
            ]
          }
        },
        "shard2": {
          "rotation": {
            "0.0": [
              0,
              90,
              0
            ],
            "2.0": [
              0,
              450,
              0
            ]
          }
        },
        "shard3": {
          "rotation": {
            "0.0": [
              0,
              180,
              0
            ],
            "2.0": [
              0,
              540,
              0
            ]
          }
        },
        "shard4": {
          "rotation": {
            "0.0": [
              0,
              270,
              0
            ],
            "2.0": [
              0,
              630,
              0
            ]
          }
        }
      }
    },
    "animation.obelisk_sentinel.attack": {
      "loop": false,
      "animation_length": 0.8,
      "bones": {
        "core": {
          "rotation": {
            "0.0": [
              0,
              0,
              0
            ],
            "0.2": [
              8,
              0,
              0
            ],
            "0.8": [
              0,
              0,
              0
            ]
          }
        },
        "shard1": {
          "rotation": {
            "0.0": [
              0,
              0,
              0
            ],
            "0.8": [
              0,
              720,
              0
            ]
          }
        },
        "shard2": {
          "rotation": {
            "0.0": [
              0,
              90,
              0
            ],
            "0.8": [
              0,
              810,
              0
            ]
          }
        },
        "shard3": {
          "rotation": {
            "0.0": [
              0,
              180,
              0
            ],
            "0.8": [
              0,
              900,
              0
            ]
          }
        },
        "shard4": {
          "rotation": {
            "0.0": [
              0,
              270,
              0
            ],
            "0.8": [
              0,
              990,
              0
            ]
          }
        }
      }
    }
  }
}
